{
  "area_size": 400.0,
  "num_uuv": 3,
  "uav_xy": [200.0, 200.0],
  "usv_initial_xy": [200.0, 200.0],
  "uuv_initial_xy": [200.0, 200.0],
  "uav_height_m": 100.0,
  "h_min_m": 50.0,
  "h_max_m": 120.0,
  "underwater_depth_m": -120.0,
  "safe_radius_m": 15.0,
  "target_initial_distance_m": 100.0,
  "usv_speed_kn": 3.9,
  "uuv_speed_kn": 7.8,
  "target_speed_kn": 1.0,
  "conversion_efficiency": 0.8,
  "drag_force_n": 2000.0,
  "connectivity_c1": 0.00007,
  "energy_balance_c2": 40.0,
  "dqn_iterations": 10000,
  "dqn_learning_rate": 0.001,
  "dqn_discount": 0.95,
  "dqn_batch_size": 128,
  "dqn_memory_capacity": 10000,
  "dqn_paper_epsilon": 0.9,
  "terminal_reward": 10.0,
  "positive_reward": 0.1,
  "negative_reward": -1.0,
  "aco_populations": 100,
  "aco_iterations": 100,
  "aco_pheromone_volatility": 0.2,
  "time_step_s": 1.0,
  "max_steps": 220,
  "random_seed": 7,
  "search_radius_per_altitude": 2.04,
  "usv_relay_fraction_to_uuv": 0.55,
  "acoustic_link_radius_m": 260.0,
  "em_link_scale_m": 260.0,
  "underwater_link_scale_m": 180.0
}
